{
  "build": {
    "content": [
      {
        "files": [
          "**/*.md"
        ],
        "exclude": [
          "**/obj/**"
        ]
      }
    ],
    "resource": [
      {
        "files": [
          "**/*.png",
          "**/*.jpg"
        ],
        "exclude": [
          "**/obj/**"
        ]
      }
    ],
    "template": [
      "op.html"
    ],
    "dest": "opwdsa",
    "globalMetadata": {
      "layout": "Conceptual",
      "breadcrumb_path": "/bcmsdn/toc.json"
    }
  }
}
